{
    "Ar36": {
        "error": 1.283252498011169,
        "error_type": "",
        "fit": "previous",
        "references": [
            {
                "exclude": false,
                "record_id": "ba-02-N-1204"
            }
        ],
        "value": 78.84902383698099
    },
    "Ar37": {
        "error": 3.744358886456154e-07,
        "error_type": "",
        "fit": "previous",
        "references": [
            {
                "exclude": false,
                "record_id": "ba-02-N-1204"
            }
        ],
        "value": 3.679758393837309e-06
    },
    "Ar38": {
        "error": 5.710033997912891e-07,
        "error_type": "",
        "fit": "previous",
        "references": [
            {
                "exclude": false,
                "record_id": "ba-02-N-1204"
            }
        ],
        "value": 1.8981784493154903e-06
    },
    "Ar39": {
        "error": 3.398264502099287e-07,
        "error_type": "",
        "fit": "previous",
        "references": [
            {
                "exclude": false,
                "record_id": "ba-02-N-1204"
            }
        ],
        "value": 8.407161861374662e-07
    },
    "Ar40": {
        "error": 4.462237423927649e-06,
        "error_type": "",
        "fit": "previous",
        "references": [
            {
                "exclude": false,
                "record_id": "ba-02-N-1204"
            }
        ],
        "value": 8.854972716915262e-05
    }
}