{
    "Ar36": {
        "error": 0.5317867519288891,
        "error_type": "",
        "fit": "previous",
        "references": [
            {
                "exclude": false,
                "record_id": "ba-02-N-1487"
            }
        ],
        "value": 52.131185906322095
    },
    "Ar37": {
        "error": 3.980808407068409e-07,
        "error_type": "",
        "fit": "previous",
        "references": [
            {
                "exclude": false,
                "record_id": "ba-02-N-1487"
            }
        ],
        "value": 3.7846491218760776e-06
    },
    "Ar38": {
        "error": 5.222948180006731e-07,
        "error_type": "",
        "fit": "previous",
        "references": [
            {
                "exclude": false,
                "record_id": "ba-02-N-1487"
            }
        ],
        "value": -2.463990140175191e-07
    },
    "Ar39": {
        "error": 2.9793796588000795e-07,
        "error_type": "",
        "fit": "previous",
        "references": [
            {
                "exclude": false,
                "record_id": "ba-02-N-1487"
            }
        ],
        "value": 2.9281894592889655e-07
    },
    "Ar40": {
        "error": 1.510772490872462e-06,
        "error_type": "",
        "fit": "previous",
        "references": [
            {
                "exclude": false,
                "record_id": "ba-02-N-1487"
            }
        ],
        "value": 3.190293739607651e-05
    }
}