{
    "Ar36": {
        "error": 0.7619933795302056,
        "error_type": "",
        "fit": "previous",
        "references": [
            {
                "exclude": false,
                "record_id": "ba-02-N-1511"
            }
        ],
        "value": 45.11818154227801
    },
    "Ar37": {
        "error": 3.669000321698858e-07,
        "error_type": "",
        "fit": "previous",
        "references": [
            {
                "exclude": false,
                "record_id": "ba-02-N-1511"
            }
        ],
        "value": 2.918282939549477e-06
    },
    "Ar38": {
        "error": 5.187794135130376e-07,
        "error_type": "",
        "fit": "previous",
        "references": [
            {
                "exclude": false,
                "record_id": "ba-02-N-1511"
            }
        ],
        "value": 5.772201193632039e-07
    },
    "Ar39": {
        "error": 3.663329376258656e-07,
        "error_type": "",
        "fit": "previous",
        "references": [
            {
                "exclude": false,
                "record_id": "ba-02-N-1511"
            }
        ],
        "value": 1.2060946043071e-06
    },
    "Ar40": {
        "error": 1.8024395763420098e-06,
        "error_type": "",
        "fit": "previous",
        "references": [
            {
                "exclude": false,
                "record_id": "ba-02-N-1511"
            }
        ],
        "value": 3.403711905309135e-05
    }
}