{
    "Ar36": {
        "error": 1.0117088093140771,
        "error_type": "",
        "fit": "previous",
        "references": [
            {
                "exclude": false,
                "record_id": "ba-02-N-783"
            }
        ],
        "value": 110.23966553865024
    },
    "Ar37": {
        "error": 3.0782653652770513e-07,
        "error_type": "",
        "fit": "previous",
        "references": [
            {
                "exclude": false,
                "record_id": "ba-02-N-783"
            }
        ],
        "value": 4.5307321311682795e-06
    },
    "Ar38": {
        "error": 5.43953347756215e-07,
        "error_type": "",
        "fit": "previous",
        "references": [
            {
                "exclude": false,
                "record_id": "ba-02-N-783"
            }
        ],
        "value": 7.926147437308468e-07
    },
    "Ar39": {
        "error": 2.786192300077249e-07,
        "error_type": "",
        "fit": "previous",
        "references": [
            {
                "exclude": false,
                "record_id": "ba-02-N-783"
            }
        ],
        "value": 1.9323677687153273e-06
    },
    "Ar40": {
        "error": 2.0536322030881784e-06,
        "error_type": "",
        "fit": "previous",
        "references": [
            {
                "exclude": false,
                "record_id": "ba-02-N-783"
            }
        ],
        "value": 4.480310841030523e-05
    }
}