{
    "Ar36": {
        "error": 1.0781540375167669,
        "error_type": "",
        "fit": "previous",
        "references": [
            {
                "exclude": false,
                "record_id": "ba-02-N-726"
            }
        ],
        "value": 131.09928401266058
    },
    "Ar37": {
        "error": 3.5326832131048563e-07,
        "error_type": "",
        "fit": "previous",
        "references": [
            {
                "exclude": false,
                "record_id": "ba-02-N-726"
            }
        ],
        "value": 3.89525616655587e-06
    },
    "Ar38": {
        "error": 5.052309368270385e-07,
        "error_type": "",
        "fit": "previous",
        "references": [
            {
                "exclude": false,
                "record_id": "ba-02-N-726"
            }
        ],
        "value": 1.246041447821448e-06
    },
    "Ar39": {
        "error": 2.6493530727392994e-07,
        "error_type": "",
        "fit": "previous",
        "references": [
            {
                "exclude": false,
                "record_id": "ba-02-N-726"
            }
        ],
        "value": 8.295582670576516e-07
    },
    "Ar40": {
        "error": 1.5576148852366883e-06,
        "error_type": "",
        "fit": "previous",
        "references": [
            {
                "exclude": false,
                "record_id": "ba-02-N-726"
            }
        ],
        "value": 9.301072802774133e-05
    }
}