{
    "AX": {
        "error": 1.1416004192253846e-06,
        "error_type": "SEM",
        "filter_outliers_dict": {
            "filter_outliers": true,
            "iterations": 1,
            "std_devs": 2
        },
        "fit": "average",
        "value": -3.740063663245614e-06
    },
    "H1": {
        "error": 9.988283539954383e-07,
        "error_type": "SEM",
        "filter_outliers_dict": {
            "filter_outliers": true,
            "iterations": 1,
            "std_devs": 2
        },
        "fit": "average",
        "value": -2.7166075019298245e-05
    },
    "H2": {
        "error": 1.6687439954666807e-06,
        "error_type": "SEM",
        "filter_outliers_dict": {
            "filter_outliers": true,
            "iterations": 1,
            "std_devs": 2
        },
        "fit": "average",
        "value": -1.5634732722754385e-05
    },
    "L1": {
        "error": 1.0455285044017103e-06,
        "error_type": "SEM",
        "filter_outliers_dict": {
            "filter_outliers": true,
            "iterations": 1,
            "std_devs": 2
        },
        "fit": "average",
        "value": -1.8862863029310342e-06
    },
    "L2": {
        "error": 0.044169532520975545,
        "error_type": "SEM",
        "filter_outliers_dict": {
            "filter_outliers": false,
            "iterations": 0,
            "std_devs": 0,
            "use_iqr_filtering": false,
            "use_standard_deviation_filtering": false
        },
        "fit": "Average",
        "fn": 300,
        "include_baseline_error": false,
        "n": 300,
        "outlier_excluded": [],
        "reviewed": true,
        "user_excluded": [],
        "value": 0.5
    }
}