{
    "Ar36": {
        "error": 5.481488147141713,
        "error_type": "SEM",
        "filter_outliers_dict": {
            "filter_outliers": true,
            "iterations": 1,
            "std_devs": 2
        },
        "fit": "linear",
        "value": 3076.8788732153953
    },
    "Ar37": {
        "error": 3.4113040598756744e-07,
        "error_type": "SEM",
        "filter_outliers_dict": {
            "filter_outliers": true,
            "iterations": 1,
            "std_devs": 2
        },
        "fit": "linear",
        "value": 3.500183822919571e-06
    },
    "Ar38": {
        "error": 4.926517877534174e-07,
        "error_type": "SEM",
        "filter_outliers_dict": {
            "filter_outliers": true,
            "iterations": 1,
            "std_devs": 2
        },
        "fit": "linear",
        "value": 7.658053626846575e-06
    },
    "Ar39": {
        "error": 2.220597025328185e-07,
        "error_type": "SEM",
        "filter_outliers_dict": {
            "filter_outliers": true,
            "iterations": 1,
            "std_devs": 2
        },
        "fit": "linear",
        "value": -2.2202032165329128e-05
    },
    "Ar40": {
        "error": 3.1762891397047277e-06,
        "error_type": "SEM",
        "filter_outliers_dict": {
            "filter_outliers": true,
            "iterations": 1,
            "std_devs": 2
        },
        "fit": "linear",
        "value": 0.015948504614295977
    }
}