{
    "Ar36": {
        "error": 52.83126380531955,
        "error_type": "SEM",
        "filter_outliers_dict": {
            "filter_outliers": false,
            "iterations": 0,
            "std_devs": 0,
            "use_iqr_filtering": false,
            "use_standard_deviation_filtering": false
        },
        "fit": "Linear",
        "fn": 60,
        "include_baseline_error": false,
        "n": 60,
        "outlier_excluded": [],
        "reviewed": true,
        "user_excluded": [],
        "value": 132796.23556556695
    },
    "Ar37": {
        "error": 1.9639735857246739e-07,
        "error_type": "SEM",
        "filter_outliers_dict": {
            "filter_outliers": false,
            "iterations": 0,
            "std_devs": 0,
            "use_iqr_filtering": false,
            "use_standard_deviation_filtering": false
        },
        "fit": "Average",
        "fn": 60,
        "include_baseline_error": false,
        "n": 60,
        "outlier_excluded": [],
        "reviewed": true,
        "user_excluded": [],
        "value": 1.8068548556016139e-06
    },
    "Ar38": {
        "error": 6.471986031243375e-07,
        "error_type": "SEM",
        "filter_outliers_dict": {
            "filter_outliers": false,
            "iterations": 0,
            "std_devs": 0,
            "use_iqr_filtering": false,
            "use_standard_deviation_filtering": false
        },
        "fit": "Linear",
        "fn": 60,
        "include_baseline_error": false,
        "n": 60,
        "outlier_excluded": [],
        "reviewed": true,
        "user_excluded": [],
        "value": 0.0004281414160158835
    },
    "Ar39": {
        "error": 1.6307578844739872e-07,
        "error_type": "SEM",
        "filter_outliers_dict": {
            "filter_outliers": false,
            "iterations": 0,
            "std_devs": 0,
            "use_iqr_filtering": false,
            "use_standard_deviation_filtering": false
        },
        "fit": "Average",
        "fn": 60,
        "include_baseline_error": false,
        "n": 60,
        "outlier_excluded": [],
        "reviewed": true,
        "user_excluded": [],
        "value": -1.7262840916979864e-05
    },
    "Ar40": {
        "error": 5.157688037358674e-05,
        "error_type": "SEM",
        "filter_outliers_dict": {
            "filter_outliers": false,
            "iterations": 0,
            "std_devs": 0,
            "use_iqr_filtering": false,
            "use_standard_deviation_filtering": false
        },
        "fit": "Linear",
        "fn": 60,
        "include_baseline_error": false,
        "n": 60,
        "outlier_excluded": [],
        "reviewed": true,
        "user_excluded": [],
        "value": 0.6836464502248902
    }
}