{
    "Ar36": {
        "error": 65.41159276914489,
        "error_type": "SEM",
        "filter_outliers_dict": {
            "filter_outliers": true,
            "iterations": 1,
            "std_devs": 2
        },
        "fit": "linear",
        "value": 132016.5768339744
    },
    "Ar37": {
        "error": 2.9539191122867983e-07,
        "error_type": "SEM",
        "filter_outliers_dict": {
            "filter_outliers": true,
            "iterations": 1,
            "std_devs": 2
        },
        "fit": "linear",
        "value": 2.034489418370674e-06
    },
    "Ar38": {
        "error": 6.4411227720112e-07,
        "error_type": "SEM",
        "filter_outliers_dict": {
            "filter_outliers": true,
            "iterations": 1,
            "std_devs": 2
        },
        "fit": "linear",
        "value": 0.0004268182758694534
    },
    "Ar39": {
        "error": 3.0679925298842176e-07,
        "error_type": "SEM",
        "filter_outliers_dict": {
            "filter_outliers": true,
            "iterations": 1,
            "std_devs": 2
        },
        "fit": "linear",
        "value": -1.8826874726819016e-05
    },
    "Ar40": {
        "error": 0.000144984444599071,
        "error_type": "SEM",
        "filter_outliers_dict": {
            "filter_outliers": true,
            "iterations": 1,
            "std_devs": 2
        },
        "fit": "linear",
        "value": 0.6823630390012261
    }
}